hrfparser/__init__.py
hrfparser/hrfparser.py
hrfparser-1.1.0.dist-info/METADATA
hrfparser-1.1.0.dist-info/WHEEL
hrfparser-1.1.0.dist-info/licenses/LICENSE
hrfparser-1.1.0.dist-info/RECORD
